django33_ninja_extra/__init__.py
django33_ninja_extra/apps.py
django33_ninja_extra/compatible.py
django33_ninja_extra/conf/__init__.py
django33_ninja_extra/conf/settings.py
django33_ninja_extra/constants.py
django33_ninja_extra/controllers/__init__.py
django33_ninja_extra/controllers/base.py
django33_ninja_extra/controllers/model/__init__.py
django33_ninja_extra/controllers/model/builder.py
django33_ninja_extra/controllers/model/endpoints.py
django33_ninja_extra/controllers/model/interfaces.py
django33_ninja_extra/controllers/model/path_resolver.py
django33_ninja_extra/controllers/model/schemas.py
django33_ninja_extra/controllers/model/service.py
django33_ninja_extra/controllers/registry.py
django33_ninja_extra/controllers/response.py
django33_ninja_extra/controllers/route/__init__.py
django33_ninja_extra/controllers/route/context.py
django33_ninja_extra/controllers/route/route_functions.py
django33_ninja_extra/dependency_resolver.py
django33_ninja_extra/details.py
django33_ninja_extra/exceptions.py
django33_ninja_extra/generic.py
django33_ninja_extra/helper.py
django33_ninja_extra/injector.py
django33_ninja_extra/lazy.py
django33_ninja_extra/logger.py
django33_ninja_extra/main.py
django33_ninja_extra/modules.py
django33_ninja_extra/operation.py
django33_ninja_extra/ordering.py
django33_ninja_extra/pagination/__init__.py
django33_ninja_extra/pagination/decorator.py
django33_ninja_extra/pagination/models/__init__.py
django33_ninja_extra/pagination/models/page_by_number.py
django33_ninja_extra/pagination/operations.py
django33_ninja_extra/permissions/__init__.py
django33_ninja_extra/permissions/base.py
django33_ninja_extra/permissions/common.py
django33_ninja_extra/py.typed
django33_ninja_extra/router.py
django33_ninja_extra/schemas/__init__.py
django33_ninja_extra/schemas/response.py
django33_ninja_extra/searching.py
django33_ninja_extra/security/__init__.py
django33_ninja_extra/security/api_key.py
django33_ninja_extra/security/http.py
django33_ninja_extra-0.1.1.dist-info/LICENSE
django33_ninja_extra-0.1.1.dist-info/METADATA
django33_ninja_extra-0.1.1.dist-info/WHEEL
django33_ninja_extra-0.1.1.dist-info/RECORD
