Metadata-Version: 2.1
Name: django33-ninja-extra
Version: 0.1.1
Summary: 增强django33_ninja，支持基于类的视图和基于函数的视图
Author: zhangdapeng
Author-email: 1156956636@qq.com
Requires-Python: >=3.12,<4.0
Classifier: Programming Language :: Python :: 3
Classifier: Programming Language :: Python :: 3.12
Classifier: Programming Language :: Python :: 3.13
